TermG/__init__.py
TermG/termg.py
termg-0.0.3.dist-info/METADATA
termg-0.0.3.dist-info/WHEEL
termg-0.0.3.dist-info/licenses/LICENSE
termg-0.0.3.dist-info/RECORD
