Metadata-Version: 2.1
Name: TermG
Version: 0.0.3
Summary: A small graphics library using text
Project-URL: Homepage, https://google.com
Project-URL: Bug Tracker, https://google.com
Author-email: PatattMan <author@example.com>
License-File: LICENSE
Classifier: License :: OSI Approved :: MIT License
Classifier: Operating System :: OS Independent
Classifier: Programming Language :: Python :: 3
Requires-Python: >=3.7
